pycasaxps/__init__.py
pycasaxps/plot.py
pycasaxps-1.0.dist-info/METADATA
pycasaxps-1.0.dist-info/RECORD
pycasaxps-1.0.dist-info/WHEEL
pycasaxps-1.0.dist-info/top_level.txt
