Metadata-Version: 2.1
Name: pycasaxps
Version: 1.0
Summary: Plotting tools for CasaXPS data
Home-page: https://github.com/jdh10791/py-casaxps
Author: Jake Huang
Author-email: jdh10791@gmail.com
License: MIT
Platform: UNKNOWN
